multibypass/cli.py
multibypass/wordlists/backup-extensions
multibypass/wordlists/spoofing-headers
multibypass/wordlists/spoofing-ips
multibypass/wordlists/url-tampering-prefixes
multibypass/wordlists/url-tampering-suffixes
multibypass/wordlists/user-agents
multibypass/wordlists/verb-tampering-arguments
multibypass/wordlists/verb-tampering-headers
multibypass/wordlists/verb-tampering-methods
multibypass/wordlists/web-extensions
multibypass-1.1.0.dist-info/licenses/LICENSE
multibypass-1.1.0.dist-info/METADATA
multibypass-1.1.0.dist-info/WHEEL
multibypass-1.1.0.dist-info/entry_points.txt
multibypass-1.1.0.dist-info/top_level.txt
multibypass-1.1.0.dist-info/RECORD
