Metadata-Version: 2.4
Name: multibypass
Version: 1.1.0
Summary: Pentest tool for bypassing restricted access using various techniques
Author-email: Greyf0x <contact@greyf0x.com>
License: MIT License
Project-URL: Homepage, https://github.com/grf0x/multibypass
Project-URL: Repository, https://github.com/grf0x/multibypass
Project-URL: Issues, https://github.com/grf0x/multibypass/issues
Requires-Python: >=3.9
License-File: LICENSE
Requires-Dist: certifi==2025.8.3
Requires-Dist: charset-normalizer==3.4.3
Requires-Dist: idna==3.10
Requires-Dist: requests==2.32.4
Requires-Dist: urllib3==2.5.0
Dynamic: license-file
